RxBagExtractor/__init__.py
RxBagExtractor/extractor.py
RxBagExtractor-0.1.6.dist-info/METADATA
RxBagExtractor-0.1.6.dist-info/WHEEL
RxBagExtractor-0.1.6.dist-info/top_level.txt
RxBagExtractor-0.1.6.dist-info/RECORD
